douyin_spider/__init__.py
douyin_spider/assign_share_url.py
douyin_spider/config.py
douyin_spider/downloaders/__init__.py
douyin_spider/downloaders/music.py
douyin_spider/downloaders/parent.py
douyin_spider/downloaders/video.py
douyin_spider/enter/__init__.py
douyin_spider/enter/hot_music.py
douyin_spider/enter/hot_positive_energy.py
douyin_spider/enter/hot_search.py
douyin_spider/enter/hot_star.py
douyin_spider/enter/hot_top.py
douyin_spider/handler/__init__.py
douyin_spider/handler/handler.py
douyin_spider/handler/media.py
douyin_spider/handler/mongodb.py
douyin_spider/handler/music.py
douyin_spider/handler/video.py
douyin_spider/models/JsonMixIn.py
douyin_spider/models/__init__.py
douyin_spider/models/address.py
douyin_spider/models/challenge.py
douyin_spider/models/collection_model.py
douyin_spider/models/music.py
douyin_spider/models/user.py
douyin_spider/models/video.py
douyin_spider/utils/__init__.py
douyin_spider/utils/common.py
douyin_spider/utils/extension.py
douyin_spider/utils/get.py
douyin_spider/utils/parse.py
douyin_spider/utils/decryption/signture.py
douyin_spider-0.0.2.dist-info/LICENSE
douyin_spider-0.0.2.dist-info/METADATA
douyin_spider-0.0.2.dist-info/WHEEL
douyin_spider-0.0.2.dist-info/top_level.txt
douyin_spider-0.0.2.dist-info/RECORD
