Metadata-Version: 2.1
Name: douyin-spider
Version: 0.0.2
Summary: One simple and easy to use crawler for DouYin
Home-page: https://github.com/ErisYoung/douyin_spider
Author: Jerry_suye
Author-email: jerry_suye@163.com
License: UNKNOWN
Platform: UNKNOWN
Classifier: Programming Language :: Python :: 3
Classifier: License :: OSI Approved :: MIT License
Classifier: Operating System :: OS Independent
Requires-Dist: aiohttp (>=3.4.4)
Requires-Dist: retrying (>=1.3.3)
Requires-Dist: motor (>=2.0.0)
Requires-Dist: tqdm (>=4.26.0)
Requires-Dist: requests (>=2.19.1)
Requires-Dist: dateparser (>=0.7.1)
